mima/__init__.py
mima-0.1.0.dist-info/LICENSE
mima-0.1.0.dist-info/WHEEL
mima-0.1.0.dist-info/METADATA
mima-0.1.0.dist-info/RECORD
