Metadata-Version: 2.1
Name: mima
Version: 0.1.0
Summary: Actor as a Service, in Python.
Home-page: https://github.com/hongqn
Author: Qiangning Hong
Author-email: hongqn@gmail.com
Classifier: License :: OSI Approved :: MIT License
Classifier: Development Status :: 1 - Planning
